setup.cfg
setup.py
pg_events/__init__.py
pg_events/__main__.py
pg_events.egg-info/PKG-INFO
pg_events.egg-info/SOURCES.txt
pg_events.egg-info/dependency_links.txt
pg_events.egg-info/entry_points.txt
pg_events.egg-info/requires.txt
pg_events.egg-info/top_level.txt
pg_events/core/__init__.py
pg_events/core/base.py
pg_events/core/build.py
pg_events/core/commands.py
pg_events/core/utils.py
pg_events/core/worker.py
pg_events/core/schemas/__init__.py
pg_events/core/schemas/event_triggers.sql
pg_events/core/schemas/triggers.sql