Metadata-Version: 1.1
Name: pg-events
Version: 0.1.7b0
Summary: Postgres events
Home-page: https://github.com/ZeroCater/pg_events
Author: ZeroCater
Author-email: tech@zerocater.com
License: MIT
Download-URL: https://github.com/ZeroCater/pg_events/tarball/0.1.7b
Keywords: postgres python django trigger listen notify events heroku connect
Platform: UNKNOWN
Classifier: License :: OSI Approved :: MIT License
Classifier: Programming Language :: Python
Classifier: Development Status :: 5 - Production/Stable
Classifier: Intended Audience :: Developers
